invenio_admin/__init__.py
invenio_admin/config.py
invenio_admin/ext.py
invenio_admin/filters.py
invenio_admin/forms.py
invenio_admin/permissions.py
invenio_admin/proxies.py
invenio_admin/views.py
invenio_admin/translations/cs/LC_MESSAGES/messages.mo
invenio_admin/translations/cs/LC_MESSAGES/messages.po
invenio_admin/translations/da/LC_MESSAGES/messages.mo
invenio_admin/translations/da/LC_MESSAGES/messages.po
invenio_admin/translations/de/LC_MESSAGES/messages.mo
invenio_admin/translations/de/LC_MESSAGES/messages.po
invenio_admin/translations/es/LC_MESSAGES/messages.mo
invenio_admin/translations/es/LC_MESSAGES/messages.po
invenio_admin/translations/fr/LC_MESSAGES/messages.mo
invenio_admin/translations/fr/LC_MESSAGES/messages.po
invenio_admin/translations/it/LC_MESSAGES/messages.mo
invenio_admin/translations/it/LC_MESSAGES/messages.po
invenio_admin-1.5.2.dist-info/licenses/AUTHORS.rst
invenio_admin-1.5.2.dist-info/licenses/LICENSE
invenio_admin-1.5.2.dist-info/METADATA
invenio_admin-1.5.2.dist-info/WHEEL
invenio_admin-1.5.2.dist-info/entry_points.txt
invenio_admin-1.5.2.dist-info/top_level.txt
invenio_admin-1.5.2.dist-info/RECORD
