Metadata-Version: 2.4
Name: invenio-admin
Version: 1.5.2
Summary: "Invenio module that adds administration panel to the system."
Home-page: https://github.com/inveniosoftware/invenio-admin
Author: CERN
Author-email: info@inveniosoftware.org
License: MIT
Keywords: invenio admin flask-admin
Platform: any
Classifier: Development Status :: 5 - Production/Stable
Requires-Python: >=3.7
License-File: LICENSE
License-File: AUTHORS.rst
Requires-Dist: Flask-Admin>=1.5.6
Requires-Dist: Flask-Menu>=0.5.0
Requires-Dist: Flask-Principal>=0.4.0
Requires-Dist: invenio-accounts>=1.2.1
Requires-Dist: invenio-base>=1.2.9
Requires-Dist: invenio-db>=1.0.9
Requires-Dist: invenio-i18n>=2.0.0
Requires-Dist: invenio-app>=1.4.0
Requires-Dist: wtforms<3.2.0
Provides-Extra: tests
Requires-Dist: pytest-black-ng>=0.4.0; extra == "tests"
Requires-Dist: invenio-theme>=1.3.4; extra == "tests"
Requires-Dist: pytest-invenio>=1.4.3; extra == "tests"
Requires-Dist: sphinx>=4.5; extra == "tests"
Requires-Dist: invenio-access>=1.0.0; extra == "tests"
Provides-Extra: docs
Provides-Extra: access
Dynamic: license-file
